pylutron/__init__.py
pylutron/_telnetlib/__init__.py
pylutron/_telnetlib/telnetlib.py
pylutron-0.2.18.dist-info/licenses/LICENSE
pylutron-0.2.18.dist-info/METADATA
pylutron-0.2.18.dist-info/WHEEL
pylutron-0.2.18.dist-info/top_level.txt
pylutron-0.2.18.dist-info/zip-safe
pylutron-0.2.18.dist-info/RECORD
